{"photo":{"id":"7228498702","secret":"e17a99b327","server":"7232","farm":8,"dateuploaded":"1337452700","isfavorite":0,"license":"5","safety_level":"0","rotation":0,"originalsecret":"29ae54c70b","originalformat":"jpg","owner":{"nsid":"56619626@N05","username":"InSapphoWeTrust","realname":"","location":"Los Angeles, California, USA","iconserver":"5283","iconfarm":6},"title":"Alicia Keys at Madame Tussaud's New York","description":"A lovely portrayal of New York's own singer-songwriter Alicia Keys, born in Hell's Kitchen, and enrolled at Columbia University until dropping out to pursue her music career full-time.\n\nMadame Tussaud's - always a tacky tourist trap, but also always a good place to test my portrait photography skills - and my prime lens (35mm f\/1.8).","visibility":{"ispublic":1,"isfriend":0,"isfamily":0},"dates":{"posted":"1337452700","taken":"2012-05-08 11:18:31","takengranularity":"0","lastupdate":"1347803629"},"views":"192","editability":{"cancomment":0,"canaddmeta":0},"publiceditability":{"cancomment":1,"canaddmeta":0},"usage":{"candownload":1,"canblog":0,"canprint":0,"canshare":1},"comments":"3","notes":{"note":[]},"people":{"haspeople":0},"tags":{"tag":[{"id":"56614286-7228498702-101887","author":"56619626@N05","raw":"2012","_content":"2012","machine_tag":0},{"id":"56614286-7228498702-440","author":"56619626@N05","raw":"New York","_content":"newyork","machine_tag":0},{"id":"56614286-7228498702-5392","author":"56619626@N05","raw":"Manhattan","_content":"manhattan","machine_tag":0},{"id":"56614286-7228498702-112821","author":"56619626@N05","raw":"Madame Tussaud's","_content":"madametussauds","machine_tag":0},{"id":"56614286-7228498702-225223","author":"56619626@N05","raw":"Alicia Keys","_content":"aliciakeys","machine_tag":0}]},"location":{"latitude":40.756865,"longitude":-73.9888,"accuracy":"13","context":"0","neighbourhood":{"_content":"Theatre District","place_id":"byMt1GpTWrhtqOpahg","woeid":"28288823"},"locality":{"_content":"New York","place_id":".skCPTpTVr.Q3WKW","woeid":"2459115"},"county":{"_content":"Manhattan","place_id":"eFEYI5ZQUL_VqqpXvg","woeid":"12589342"},"region":{"_content":"New York","place_id":"ODHTuIhTUb75gdBu","woeid":"2347591"},"country":{"_content":"United States","place_id":"nz.gsghTUb4c2WAecA","woeid":"23424977"},"place_id":"byMt1GpTWrhtqOpahg","woeid":"28288823"},"geoperms":{"ispublic":1,"iscontact":0,"isfriend":0,"isfamily":0},"urls":{"url":[{"type":"photopage","_content":"http:\/\/www.flickr.com\/photos\/skinnylawyer\/7228498702\/"}]},"media":"photo"},"stat":"ok"}